openMystatAPI/__init__.py
openMystatAPI/api.py
openMystatAPI/mystat_types.py
openMystatAPI-0.0.1.dist-info/METADATA
openMystatAPI-0.0.1.dist-info/WHEEL
openMystatAPI-0.0.1.dist-info/top_level.txt
openMystatAPI-0.0.1.dist-info/RECORD
