Metadata-Version: 2.1
Name: openMystatAPI
Version: 0.0.1
Summary: Unofficial, but open API realisation on python of mystat.itstep.org, a site for students of ITSTEP.
Home-page: https://github.com/Vezono/python-mystat-api
Author: Vezono
Author-email: gbball.baas@gmail.com
License: UNKNOWN
Platform: UNKNOWN
Classifier: Programming Language :: Python :: 3
Classifier: License :: OSI Approved :: MIT License
Classifier: Operating System :: OS Independent
Requires-Python: >=3.6
